{"text": "Must the name mean something", "loudness": {"left": ["lightgray", "lightgray", "rgb(69, 170, 227)", "lightgray", "rgb(69, 170, 227)"], "right": ["lightgray", "lightgray", "rgb(69, 170, 227)", "lightgray", "rgb(69, 170, 227)"], "rlt": "Higher"}, "average_pitch": {"left": ["lightgray", "lightgray", "rgb(69, 170, 227)", "lightgray", "rgb(69, 170, 227)"], "right": ["lightgray", "lightgray", "rgb(69, 170, 227)", "lightgray", "rgb(69, 170, 227)"], "rlt": "Higher"}, "pitch_range": {"left": ["lightgray", "lightgray", "rgb(69, 170, 227)", "lightgray", "rgb(69, 170, 227)"], "right": ["lightgray", "lightgray", "rgb(69, 170, 227)", "lightgray", "rgb(69, 170, 227)"], "rlt": "Higher"}, "speed": {"left": ["rgb(69, 170, 227)", "rgb(69, 170, 227)", "rgb(69, 170, 227)", "rgb(69, 170, 227)", "lightgray"], "right": ["rgb(69, 170, 227)", "rgb(69, 170, 227)", "rgb(69, 170, 227)", "rgb(69, 170, 227)", "lightgray"], "rlt": "Shorter"}, "pauses": {"left": ["lightgray", "rgb(69, 170, 227)", "rgb(69, 170, 227)", "rgb(69, 170, 227)", "white"], "right": ["lightgray", "rgb(69, 170, 227)", "rgb(69, 170, 227)", "rgb(69, 170, 227)", "white"], "rlt": "Lower"}, "target_emotion": "Happy", "counterfactual_emotion": "Sad", "tgt_word_clips": ["10/word_clips_3/tgt_must_0.wav", "10/word_clips_3/tgt_the_1.wav", "10/word_clips_3/tgt_name_2.wav", "10/word_clips_3/tgt_mean_3.wav", "10/word_clips_3/tgt_something_4.wav"], "cf_word_clips": ["10/word_clips_3/cf_must_0.wav", "10/word_clips_3/cf_name_1.wav", "10/word_clips_3/cf_means_2.wav", "10/word_clips_3/cf_something_3.wav"], "tgt_pause_word_clips": ["10/word_clips_3/tgt_consecutive_must_the_0.wav", "10/word_clips_3/tgt_consecutive_the_name_1.wav", "10/word_clips_3/tgt_consecutive_name_mean_2.wav", "10/word_clips_3/tgt_consecutive_mean_something_3.wav"], "cf_pause_word_clips": ["10/word_clips_3/cf_consecutive_must_name_0.wav", "10/word_clips_3/cf_consecutive_name_means_1.wav", "10/word_clips_3/cf_consecutive_means_something_2.wav"], "target_audio_path": "10/word_clips_3/tgt_3.wav", "counterfactual_audio_path": "10/word_clips_3/cf_3.wav"}